setup.py
runners/__init__.py
runners/lock_helper.py
runners.egg-info/PKG-INFO
runners.egg-info/SOURCES.txt
runners.egg-info/dependency_links.txt
runners.egg-info/requires.txt
runners.egg-info/top_level.txt