Metadata-Version: 1.0
Name: runners
Version: 0.0.1
Summary: Help with running stuff
Home-page: https://github.com/EDITD/runners
Author: EDITD
Author-email: engineering@editd.com
License: LICENSE.txt
Platform: UNKNOWN
